quantinuum_qircheck/__init__.py
quantinuum_qircheck/api.py
quantinuum_qircheck/py.typed
quantinuum_qircheck/qircheck.py
quantinuum_qircheck-0.4.0.dist-info/licenses/LICENSE
tests/check_test.py
tests/testfile.wasm
tests/qir/invalid/invalid_1.ll
tests/qir/invalid/invalid_2.ll
tests/qir/invalid/test_pytket_qir_16-QIRProfile.ADAPTIVE_CREGSIZE.ll
tests/qir/invalid/test_pytket_qir_conditional_15-block-QIRProfile.ADAPTIVE_CREGSIZE.ll
tests/qir/invalid/test_pytket_qir_conditional_16-block-QIRProfile.ADAPTIVE_CREGSIZE.ll
tests/qir/invalid/test_pytket_qir_conditional_17-block-QIRProfile.ADAPTIVE_CREGSIZE.ll
tests/qir/invalid/test_pytket_qir_wasm_2-QIRProfile.ADAPTIVE_CREGSIZE.ll
tests/qir/invalid/test_pytket_qir_wasm_3-QIRProfile.ADAPTIVE_CREGSIZE.ll
tests/qir/invalid/test_pytket_qir_wasm_4-QIRProfile.ADAPTIVE_CREGSIZE.ll
tests/qir/invalid/test_pytket_qir_wasm_5-QIRProfile.ADAPTIVE_CREGSIZE.ll
tests/qir/invalid/test_pytket_qir_wasm_6-QIRProfile.ADAPTIVE_CREGSIZE.ll
tests/qir/valid/test_pytket_qir-QIRProfile.ADAPTIVE.ll
tests/qir/valid/test_pytket_qir-QIRProfile.ADAPTIVE_CREGSIZE.ll
tests/qir/valid/test_pytket_qir-QIRProfile.AZUREADAPTIVE.ll
tests/qir/valid/test_pytket_qir-QIRProfile.BASE.ll
tests/qir/valid/test_pytket_qir-QIRProfile.PYTKET.ll
tests/qir/valid/test_pytket_qir_10-QIRProfile.ADAPTIVE.ll
tests/qir/valid/test_pytket_qir_10-QIRProfile.ADAPTIVE_CREGSIZE.ll
tests/qir/valid/test_pytket_qir_10-QIRProfile.AZUREADAPTIVE.ll
tests/qir/valid/test_pytket_qir_10-QIRProfile.PYTKET.ll
tests/qir/valid/test_pytket_qir_11-QIRProfile.ADAPTIVE.ll
tests/qir/valid/test_pytket_qir_11-QIRProfile.ADAPTIVE_CREGSIZE.ll
tests/qir/valid/test_pytket_qir_11-QIRProfile.AZUREADAPTIVE.ll
tests/qir/valid/test_pytket_qir_11-QIRProfile.PYTKET.ll
tests/qir/valid/test_pytket_qir_12-QIRProfile.ADAPTIVE.ll
tests/qir/valid/test_pytket_qir_12-QIRProfile.ADAPTIVE_CREGSIZE.ll
tests/qir/valid/test_pytket_qir_12-QIRProfile.AZUREADAPTIVE.ll
tests/qir/valid/test_pytket_qir_12-QIRProfile.PYTKET.ll
tests/qir/valid/test_pytket_qir_13-QIRProfile.ADAPTIVE.ll
quantinuum_qircheck-0.4.0.dist-info/METADATA
quantinuum_qircheck-0.4.0.dist-info/WHEEL
quantinuum_qircheck-0.4.0.dist-info/top_level.txt
quantinuum_qircheck-0.4.0.dist-info/RECORD
