Metadata-Version: 2.4
Name: quantinuum_qircheck
Version: 0.4.0
Summary: Package to check QIR for compatibility with quantinuum devices
Author: Quantinuum
Maintainer-email: TKET development team <tket-support@quantinuum.com>
License:                                  Apache License
Project-URL: Repository, https://github.com/CQCL/quantinuum-qircheck
Project-URL: Tracker, https://github.com/CQCL/quantinuum-qircheck/issues
Classifier: Environment :: Console
Classifier: Programming Language :: Python :: 3.10
Classifier: Programming Language :: Python :: 3.11
Classifier: Programming Language :: Python :: 3.12
Classifier: License :: OSI Approved :: Apache Software License
Classifier: Operating System :: MacOS :: MacOS X
Classifier: Operating System :: POSIX :: Linux
Classifier: Operating System :: Microsoft :: Windows
Classifier: Intended Audience :: Developers
Classifier: Intended Audience :: Science/Research
Classifier: Topic :: Scientific/Engineering
Requires-Python: <3.13,>=3.10
License-File: LICENSE
Requires-Dist: pyqir~=0.10.9
Provides-Extra: test
Requires-Dist: pytest; extra == "test"
Dynamic: license-file
